QNCP-1.11.5.data/data/dlls/FTD3XX.dll
QNCP-1.11.5.data/data/dlls/libusb0.dll
QNCP-1.11.5.data/data/dlls/tdcbase_64bit.dll
qncp/__init__.py
qncp/acq.py
qncp/device.py
qncp/gen.py
qncp/models.py
qncp/opt.py
qncp/optics.py
qncp/redpitaya.py
qncp/search.py
qncp/services.py
qncp/storage.py
QNCP-1.11.5.dist-info/METADATA
QNCP-1.11.5.dist-info/WHEEL
QNCP-1.11.5.dist-info/top_level.txt
QNCP-1.11.5.dist-info/RECORD
